{"id": "151767", "name": "Carman Lyrics Quiz | Carman | 20 Questions", "type": "", "difficulty": "Very Easy", "tags": ["Home", "Quizzes", "Music Trivia", "  Music A-C", "Carman"], "questions": [{"text": "\"We don't know what will find. Deep behind enemy lines.\"", "correct": "Mission 3:16", "options": ["R.I.O.T.", "My Story", "Whiter Than Snow"], "explanation": "\n\n\nMission 3:16.\n\n\tJohn 3:16 \"For God so loved the world he gave his only begotten son that whosoever believeth in Him shall have everlasting light.\" \n"}, {"text": "\"Send a giant out, we'll take him down with the Word and the Spirit.\"", "correct": "People of God", "options": ["My Story", "The River", "Who's In the House"], "explanation": "\n\n\nPeople of God.\n\n\tThis song is found on Carman's \"Mission 3:16\" CD. \n"}, {"text": "\"There'll never be a time that He would ever turn his back on me.\"", "correct": "Never Be", "options": ["We Are Not Ashamed", "There Is a God", "Jesus Is the Lamb"], "explanation": "\n\n\nNever Be.\n\n\tThis is a beautiful song about how great God's love is for all of us. \n"}, {"text": "\"Lord, you know I love you, love you from the bottom of my heart.\"", "correct": "Jesus is the Lamb", "options": ["The Prayer Anthem", "We Are Not Ashamed", "Mission 3:16"], "explanation": "\n\n\nJesus is the Lamb.\n\n\tThis song is also on the \"Mission 3:16\" CD. \n"}, {"text": "\"God, You see this worthless piece of trash over here?\"", "correct": "The Courtroom", "options": ["Do I Do", "R.I.O.T.", "Never Be"], "explanation": "\n\n\nThe Courtroom.\n\n\tIt is the Devil who is saying that line in \"The Courtroom\". This is one of my favorite Carman songs. It's about the importance of having your name written in \"The Lambs Book of Life\". \n"}, {"text": "\"After many plague, people fled and then they headed for the promise land.\"", "correct": "Do I Do", "options": ["Never Be", "There is a God", "Jesus is the Lamb"], "explanation": "\n\n\nDo I Do.\n\n\tThis song is also found on the \"Mission 3:16\" CD. Carman sings about trusting God in this song. \"Do I do yes, I say, trust in you, Lord all the way.\" \n"}, {"text": "\"Remember that you're not alone wiith the cross to bear each day.\"", "correct": "We Are Not Ashamed", "options": ["Never Be", "Sunday School Rock", "The River"], "explanation": "\n\n\nWe Are Not Ashamed.\n\n\tAccording to the CD booklet, he sang this song on the \"March for Jesus\". I can't think of a more fitting song to sing than one proclaiming \"We are not ashamed of the Gospel or His name.\" \n"}, {"text": "\"Lead me not into temptation.\"", "correct": "The Prayer Anthem", "options": ["All in Life", "America Again", "My Story"], "explanation": "\n\n\nThe Prayer Anthem.\n\n\tThe Lord's Prayer (which this song comes from) can be found in Matthew 6:9-13. \n"}, {"text": "\"The rod of God will stop the attack.\"", "correct": "Slam", "options": ["R.I.O.T.", "Marchin' and Movin'", "Amen"], "explanation": "\n\n\nSlam.\n\n\tThis song also comes from the \"Mission 3:16\" CD. Carman became a Christian after seeing an \"Andrae Crouch\" concert. It was then that he gave his life to Jesus. \n"}, {"text": "\"Help me remember this truth I've learned.\"", "correct": "All in Life", "options": ["Great God", "The River", "People of God"], "explanation": "\n\n\nAll in Life.\n\n\tThis is a great song because sometimes we all slip and we need God to help us to \"remember what we've learned.\" \n"}, {"text": "\"With the facts we're gonna spread God's word.\"", "correct": "R.I.O.T.", "options": ["Slam", "Amen", "Marchin' and Movin'"], "explanation": "\n\n\nR.I.O.T.\n\n\tR.I.O.T. stands for Righteous Invasion of Truth. \n"}, {"text": "\"Giving glory to the Lord today.\"", "correct": "My Story", "options": ["Great God", "There is a God", "Amen"], "explanation": "\n\n\nMy Story.\n\n\tCarman was born in New Jersey. \n"}, {"text": "\"There is an answer to all answers.\"", "correct": "There is a God", "options": ["Amen", "The River", "Great God"], "explanation": "\n\n\nThere is a God.\n\n\tCarman has been performing for over 25 years. \n"}, {"text": "\"Come on everybody, listen to my story. Story about my Jesus.\"", "correct": "Amen", "options": ["Sunday School Rock", "There is a God", "My Story"], "explanation": "\n\n\nAmen.\n\n\tAmen means \"so be it.\" It is the very last word in the Bible. \n"}, {"text": "\"God holds up the universe.\"", "correct": "Great God", "options": ["There is a God", "Slam", "Amen"], "explanation": "\n\n\nGreat God.\n\n\tIn 2001, \"Carman: The Champion\" become the longest running Christian movie in theatres. \n"}, {"text": "\"It doesn't matter who you are.\"", "correct": "The River", "options": ["Whiter than Snow", "My Story", "There is a God"], "explanation": "\n\n\nThe River.\n\n\tThis song is on the \"R.I.O.T.\" CD. It is also done beautifully in Spanish (El Rio) on his \"Lo Mejor\" CD. \n"}, {"text": "\"The kingdom of God is on a forceful advance.\"", "correct": "Marchin' and Movin'", "options": ["Slam", "Sunday School Rock", "R.I.O.T."], "explanation": "\n\n\nMarchin' and Movin'.\n\n\tThis song is on his \"America Again\" CD. \n"}, {"text": "\"The bottom line, the way to win: is up with Jesus, down with sin.\"", "correct": "Sunday School Rock", "options": ["Mission 3:16", "America Again", "Slam"], "explanation": "\n\n\nSunday School Rock.\n\n\tThis is a great song about how important Jesus is to us. \"Only Christ can set you free.\" \n"}, {"text": "\"The only hope for America is Jesus.\"", "correct": "America Again", "options": ["Great God", "My Story", "Marchin' and Movin'"], "explanation": "\n\n\nAmerica Again.\n\n\tThis is the first Carman song I ever heard. It is extremely powerful. \n"}, {"text": "\"Ezekiel, Daniel all across the nation say.\"", "correct": "Memorize the 66 Books", "options": ["We Are Not Ashamed", "Amen", "My Story"], "explanation": "\n\n\nMemorize the 66 Books.\n\n\tThis song is on the \"Yo! Kidz\" CD. It helps children remember the 66 Books of the Bible. \r Much of my info came from the Carman Ministries website at www.carman.org. You might wish to check it out to learn more about Carman and his ministries. \r I hope you enjoyed the quiz. \n"}]}