{"id": "164739", "name": "Get Your Head Around These! Quiz | Brain Teasers | 5 Questions", "type": "", "difficulty": "Very Easy", "tags": ["Home", "Quizzes", "Brain Teasers Trivia", " Riddles"], "questions": [{"text": "I can be seen when it's cold, but not when hot.\t\t\t\nYou need me to live - take your last and you're not.", "correct": "breath & breaths", "options": [], "explanation": "\n\n\nbreath & breaths.\n\n\tBreath is visible in a cold atmosphere because the moisture within it condenses. \n"}, {"text": "If one=3, two=3, three=5, and four=4, what do five + six = ?", "correct": "seven & 7  & five & 5", "options": [], "explanation": "\n\n\nseven & 7  & five & 5.\n\n\tThe numbers relate to the number of letters in each word: one=3 (letters), two=3 (letters) etc.  Therefore, five(=4) + six(=3) = 7 (letters).\rAn alternate interpretation would be five (=4) + six (=3) = seven (=5)(letters in the word seven). \n"}, {"text": "I sound like a word of one letter, but I'm actually three.\nLook the same from both ends - I'm a palindrome  you  see.", "correct": "eye & ewe", "options": [], "explanation": "\n\n\neye & ewe.\n\n"}, {"text": "Take me from there, and you end up here.\n", "correct": "t & the letter t & letter t", "options": [], "explanation": "\n\n\nt & the letter t & letter t.\n\n\tRemove the letter 't' from there and you get here. \n"}, {"text": "Add a letter to one, place it with care.\nUse the right letter - it's no longer there.", "correct": "gone & none & g & n", "options": [], "explanation": "\n\n\ngone & none & g & n.\n\n\tAdd a g-one, or n-one. \n"}]}