{"id": "18549", "name": "LesserKnown Works and Authors Quiz | Authors and their Works | 10 Questions", "type": "", "difficulty": "Very Easy", "tags": ["Home", "Quizzes", "Literature Trivia", "Authors and their Works", "Less Familiar Works"], "questions": [{"text": "'The Mayor of Casterbridge' is one of the novels written by this author.", "correct": "Thomas Hardy", "options": ["Walter Scott", "Joseph Conrad", "Herman Melville"], "explanation": "\n\n\nThomas Hardy.\n\n\tIt's not one of his most famous, but it's good reading. \n"}, {"text": "'The Idiot' is also a lesser known work by a prominent author.", "correct": "Fyodor Dostoevsky", "options": ["James Joyce", "Leo Tolstoi", "Albert Camus"], "explanation": "\n\n\nFyodor Dostoevsky.\n\n\tAfter 'Crime and Punishment' and 'Brothers Karamazov', people struggle to remember other works. \n"}, {"text": "'Tortilla Flat' was written by this American author.", "correct": "John Steinbeck", "options": ["Nathaniel Hawthorne", "William Faulkner", "Ernest Hemingway"], "explanation": "\n\n\nJohn Steinbeck.\n\n\tThey made a movie out of it. \n"}, {"text": "'Dodsworth' also was written by an American author.", "correct": "Sinclair Lewis", "options": ["F Scott Fitzgerald", "Theodore Dreiser", "Virginia Woolf"], "explanation": "\n\n\nSinclair Lewis.\n\n\tBetter known for 'Arrowsmith' and 'Main Street' \n"}, {"text": "'Barnaby Rudge' is the product of a prolific writer.", "correct": "Charles Dickens", "options": ["Edgar Allan Poe", "Thomas Mann", "Thomas Wolfe"], "explanation": "\n\n\nCharles Dickens.\n\n\tHow many did Dickens write? \n"}, {"text": "Who is the author of the 'Tarzan' stories?", "correct": "Edgar Rice Burroughs", "options": ["G.K. Chesteron", "Hervey Allen", "Ambrose Bierce"], "explanation": "\n\n\nEdgar Rice Burroughs.\n\n\tAllen did 'Anthony Adverse'. \n"}, {"text": "Who wrote 'Ben-Hur'?", "correct": "Lew Wallace", "options": ["James M. Cain", "James Agee", "Lloyd C. Douglas"], "explanation": "\n\n\nLew Wallace.\n\n\tAgee did 'A Death in the Family'. \n"}, {"text": "Who wrote 'The Bridge of San Luis Rey'?", "correct": "Thornton Wilder", "options": ["Alexander Dumas", "Rudyard Kipling", "Victor Hugo"], "explanation": "\n\n\nThornton Wilder.\n\n\tHe is better known for 'Our Town'. \n"}, {"text": "Who wrote 'Pudd'nhead Wilson'?", "correct": "Mark Twain", "options": ["D.H. Lawrence", "Jonathan Swift", "Robert Louis Stevenson"], "explanation": "\n\n\nMark Twain.\n\n\tIt wasn't just Tom and Huck. \n"}, {"text": "Who wrote 'Men against the Sea'?", "correct": "Nordhoff and Hall", "options": ["Burdick and Lederer", "Fletcher Knebel", "Allen Drury"], "explanation": "\n\n\nNordhoff and Hall.\n\n\tAlong with 'Pitcairn island', this was part of the 'Mutiny on the Bounty' trilogy. \n"}]}