{"id": "230226", "name": "Literature Quiz: The Pretty Committee Strikes Back: 10 Questions | Harrison, Lisi", "type": "", "difficulty": "Very Easy", "tags": ["Home", "Quizzes", "Literature Trivia", "Harrison, Lisi", "Individual Clique Books"], "questions": [{"text": "What is Layne's food obsession?", "correct": "go-gurt", "options": ["oatmeal", "popcorn and mustard", "popsicles"], "explanation": "\n\n\ngo-gurt.\n\n\tHer food obsession was oatmeal in the book \"The Clique\". It was popsicles in the book \"Revenge of the Wannabees\". It was popcorn and mustard in the book \"Best Friends For Never\". \n"}, {"text": "Chris likes Claire.", "correct": "false", "options": ["t", "f"], "explanation": "\n\n\nfalse.\n\n\tJosh likes Claire, but she likes Cam. \n"}, {"text": "Who does Alicia like?", "correct": "Josh", "options": ["Cam", "Chris", "Derrington"], "explanation": "\n\n\nJosh.\n\n\tAlicia like Josh but Josh likes Claire. \n"}, {"text": "Who holds a secret kissing clinic?", "correct": "Massie", "options": ["Claire", "Dylan", "Kristen"], "explanation": "\n\n\nMassie.\n\n\tShe holds the clinic so she can get her reputation back. \n"}, {"text": "Kristen gets her period.", "correct": "false", "options": ["t", "f"], "explanation": "\n\n\nfalse.\n\n\tLayne gets her period. \n"}, {"text": "How does Claire get Cam back?", "correct": "she sneaks over to his cabin", "options": ["she brings him sours", "she asks him if he wants her back", "she doesn't get him back"], "explanation": "\n\n\nshe sneaks over to his cabin.\n\n\tShe dresses up like a boy, goes over to his cabin, and explains everything. \n"}, {"text": "The trip they went on was to Lake George.", "correct": "false", "options": ["t", "f"], "explanation": "\n\n\nfalse.\n\n\tThey went to Lake Placid. \n"}, {"text": "Claire kisses Cam.", "correct": "true", "options": ["t", "f"], "explanation": "\n\n\ntrue.\n\n\tShe kisses Cam when he sneaks over to her cabin dressed like a girl. \n"}, {"text": "What color rhinestones does Layne put on her sneakers?", "correct": "black", "options": ["pink", "yellow", "red"], "explanation": "\n\n\nblack.\n\n\tClaire put pink rhinestones on her sneakers. \n"}, {"text": "Why was Dylan traumatized?", "correct": "She saw her mom kissing her geography teacher", "options": ["Kristen told her sad news", "Chris liked someone else instead of her", "She was never traumatized, Massie was"], "explanation": "\n\n\nShe saw her mom kissing her geography teacher.\n\n\tHer geography teacher is Mr. Myner. \n"}]}