{"id": "286", "name": "What Country Were These Stars Born In? Trivia Quiz | Celebrities | 10 Questions", "type": "", "difficulty": "Very Easy", "tags": ["Home", "Quizzes", "Celebrity Trivia", "Celebrities Mixture", "    Place of Origin"], "questions": [{"text": "Mel Gibson was born in which country?", "correct": "United States", "options": ["Wales", "Australia", "England"], "explanation": "\n\n\nUnited States.\n\n\tHe was born in Peekskill, New York. \n"}, {"text": "Sean Connery was born in which country?", "correct": "Scotland", "options": ["Wales", "England", "United States"], "explanation": "\n\n\nScotland.\n\n\tHe was born Edinburgh, Scotland. \n"}, {"text": "Russell Crowe, Academy Award nominee for 'The Insider', was born in which country?", "correct": "New Zealand", "options": ["Tasmania", "Australia", "United States"], "explanation": "\n\n\nNew Zealand.\n\n\tEven though considered to be Australian, he was born in New Zealand before moving to Australia at a very young age. \n"}, {"text": "Sophia Loren was born in which country?", "correct": "Italy", "options": ["France", "Greece", "United States"], "explanation": "\n\n\nItaly.\n\n\tShe was born in Rome, Italy. \n"}, {"text": "Michael J. Fox was born in which country?", "correct": "Canada", "options": ["United States", "Iceland", "Japan"], "explanation": "\n\n\nCanada.\n\n\tHe was born in Edmonton, Alberta, Canada. \n"}, {"text": "Nicole Kidman, former wife of Tom Cruise, was born in which country?", "correct": "United States", "options": ["England", "Australia", "Scotland"], "explanation": "\n\n\nUnited States.\n\n\tShe was born in Honolulu, Hawaii. \n"}, {"text": "Lou Diamond Phillips, star of 'La Bamba', was born in which country?", "correct": "Phillipines", "options": ["Mexico", "United States", "Peru"], "explanation": "\n\n\nPhillipines.\n\n\tHe was born in Subic Bay Naval Station, Phillipines. \n"}, {"text": "Desi Arnaz was born in which country?", "correct": "Cuba", "options": ["United States", "Puerto Rico", "Haiti"], "explanation": "\n\n\nCuba.\n\n\tHe was born in Santiago, Cuba. \n"}, {"text": "John Candy was born in which country?", "correct": "Canada", "options": ["Iceland", "United States", "Mexico"], "explanation": "\n\n\nCanada.\n\n\tHe Was born in Newmarket, Ontario, Canada. \n"}, {"text": "Bruce Willis was born in which country?", "correct": "West Germany", "options": ["United States", "France", "Mexico"], "explanation": "\n\n\nWest Germany.\n\n\tHe was born in Idar-Oberstein, Germany. \n"}]}