{"id": "30896", "name": "Rock Groups And Their Singers Quiz | Lead Singers | 10 Questions", "type": "", "difficulty": "Very Easy", "tags": ["Home", "Quizzes", "Music Trivia", "Lead Singers", "Difficult Lead Singers"], "questions": [{"text": "Motley Crue", "correct": "Vince Neil", "options": ["Nikki Sixx", "Mick Mars", "Tommy Lee"], "explanation": "\n\n\nVince Neil.\n\n"}, {"text": "Poison", "correct": "Bret Michaels", "options": ["Rikki Rockett", "Bobby Dall", "C.C. DeVille"], "explanation": "\n\n\nBret Michaels.\n\n"}, {"text": "Red Hot Chili Peppers", "correct": "Anthony Kiedis", "options": ["Chad Smith", "Dave Navarro", "John Frusciante"], "explanation": "\n\n\nAnthony Kiedis.\n\n"}, {"text": "Van Halen's 1st", "correct": "David Lee Roth", "options": ["Alex Van Halen", "Sammy Hagar", "Eddie Van Halen"], "explanation": "\n\n\nDavid Lee Roth.\n\n"}, {"text": "Creed", "correct": "Scott Stapp", "options": ["Scott Phillips", "Mark Tremonti", "Brian Marshall"], "explanation": "\n\n\nScott Stapp.\n\n"}, {"text": "Metallica", "correct": "James Hetfield", "options": ["Kirk Hamett", "Jason Newsted", "Lars Ulrich"], "explanation": "\n\n\nJames Hetfield.\n\n"}, {"text": "Black Sabbath's 2nd", "correct": "Ronnie James Dio", "options": ["Tony Iommi", "Ozzy Osbourne", "Bill Ward"], "explanation": "\n\n\nRonnie James Dio.\n\n"}, {"text": "Limp Bizkit", "correct": "Fred Durst", "options": ["Sam Rivers", "Wes Borland", "John Otto"], "explanation": "\n\n\nFred Durst.\n\n"}, {"text": "Papa Roach", "correct": "Coby Dick", "options": ["Jerry Horton", "Tobin Esperance", "Dave Buckner"], "explanation": "\n\n\nCoby Dick.\n\n"}, {"text": "Godsmack", "correct": "Sully Erna", "options": ["Tommy Stewart", "Tony Rambola", "Robbie Merrill"], "explanation": "\n\n\nSully Erna.\n\n"}]}