{"id": "37163", "name": "Judgment Night Quiz | Movies | 10 Questions", "type": "", "difficulty": "Very Easy", "tags": ["Home", "Quizzes", "Movie Trivia", "   Movies H-K", "J"], "questions": [{"text": "Where are the four friends going at the beginning of the film?", "correct": "To a boxing match", "options": ["To a football match", "To a night club", "To a birthday party"], "explanation": "\n\n\nTo a boxing match.\n\n"}, {"text": "What is the name of the leader of the gangsters?", "correct": "Fallon", "options": ["Jones", "Sykes", "Brody"], "explanation": "\n\n\nFallon.\n\n\tHe is played by Denis Leary and is both terrific and terrifying at the same time. \n"}, {"text": "When the gangsters are looking for the four friends in the train yard, what is not one of the things that the leader of the gangsters yells out to them?", "correct": "Don't try to hide", "options": ["Don't move", "Don't whisper", "Don't even breathe"], "explanation": "\n\n\nDon't try to hide.\n\n"}, {"text": "Which one of the friends is the most unathletic?", "correct": "Ray", "options": ["John", "Mike", "Frank"], "explanation": "\n\n\nRay.\n\n"}, {"text": "When Ray tries to negotiate with the gangsters, how much money does he offer them at first?", "correct": "{$100,000}", "options": ["$100,000", "$300,000", "$200,000", "$400,000"], "explanation": "\n\n\n{$100,000}.\n\n\tWhen the leader doesn't accept this, Ray ups it to {$200,000} plus his ring as a deposit. \n"}, {"text": "Which one of the four friends has become a sensitive family man?", "correct": "Frank", "options": ["John", "Ray", "Mike"], "explanation": "\n\n\nFrank.\n\n\tFrank is played by Emilio Estevez. \n"}, {"text": "When Mike persuades the others to fight back against the gangsters, how does he kill Sykes?", "correct": "He shoots him", "options": ["He drowns him", "He stabs him", "He hits him over the head with a pole"], "explanation": "\n\n\nHe shoots him.\n\n\tMike shoots Sykes when they are in the sewers. \n"}, {"text": "How do the four friends get the attention of the authorities?", "correct": "They break into a store and the security alarm goes off", "options": ["They fire their gun repeatedly on the street", "They loot a store", "They don't"], "explanation": "\n\n\nThey break into a store and the security alarm goes off.\n\n"}, {"text": "Who eventually faces Fallon and kills him?", "correct": "Frank", "options": ["Ray", "Mike", "John"], "explanation": "\n\n\nFrank.\n\n"}, {"text": "How many of the friends are killed?", "correct": "One", "options": [], "explanation": "\n\n\nOne.\n\n\tRay is the only one that gets killed. He gets thrown off a building. \n"}]}