{"id": "45516", "name": "Mixed Bag 5 Online Trivia | Mixed 10 Q. Difficult [C] | 10 Questions", "type": "", "difficulty": "Very Easy", "tags": ["Home", "Quizzes", "General Knowledge Trivia", "Mixed 10 Questions", "  Mixed 10 Q. Difficult [C]"], "questions": [{"text": "The crew of the Enterprise on TV's original 'Star Trek' numbers how many?", "correct": "430", "options": ["210", "360", "300"], "explanation": "\n\n\n430.\n\n\t'Star Trek' was on TV from 1966 to 1969 starring William Shatner and Leonard Nimoy among others. \n"}, {"text": "William Gargan played what detective on radio and TV?", "correct": "Martin Kane", "options": ["Boston Blackie", "Mike Hammer", "Sam Spade"], "explanation": "\n\n\nMartin Kane.\n\n\tMartin Kane was also played by Lloyd Nolan, Lee Tracy and Mark Stevens. \n"}, {"text": "Which brand of cigarette sponsored radio's 'Your Hit Parade'?", "correct": "Lucky Strike", "options": ["Old Gold", "Winston", "Salem"], "explanation": "\n\n\nLucky Strike.\n\n\tIt was on from 1950 to 1974 first on radio and then on television. \n"}, {"text": "How many years did it take to build Chicago's Sears (Willis) Tower?", "correct": "3", "options": ["1", "9", "5"], "explanation": "\n\n\n3.\n\n\tIn 1973 Sears opened its new headquarters there. \n"}, {"text": "In what state is Saranac Black and Tan beer produced?", "correct": "New York", "options": ["Vermont", "Maryland", "Florida"], "explanation": "\n\n\nNew York.\n\n\tIt is northeastern New York near Lake Placid. \n"}, {"text": "The Black Sea and the White Sea are both located on which continent?", "correct": "Europe", "options": ["South America", "North America", "Africa"], "explanation": "\n\n\nEurope.\n\n\tThe Black Sea is between southeastern Europe and Asia Minor while the White Sea is in Russia. \n"}, {"text": "Rich boy Rollo, in the comic strip 'Nancy', has what color hair?", "correct": "Yellow", "options": ["Red", "Brown", "Black"], "explanation": "\n\n\nYellow.\n\n"}, {"text": "Name the snack food that the Indians introduced to the colonists.", "correct": "Popcorn", "options": ["Potato chips", "Peanuts", "Raisins"], "explanation": "\n\n\nPopcorn.\n\n\tThe first European explorers described the Indians as using it for food, hair decoration and scattering it for religious ceremonies. \n"}, {"text": "(True or False) Hitler planned to rebuild Berlin and call it Germania?", "correct": "True & T", "options": [], "explanation": "\n\n\nTrue & T.\n\n"}, {"text": "The gold supply of the United States is stored at Fort Knox. Where is the silver stored?", "correct": "West Point", "options": [], "explanation": "\n\n\nWest Point.\n\n\tMost of the silver mined today is in conjunction with lead or copper mining with silver being a by-product. \n"}]}