{"id": "48993", "name": "A Nice Basin of Gruel Trivia Game | Authors | 10 Questions", "type": "", "difficulty": "Very Easy", "tags": ["Home", "Quizzes", "Literature Trivia", "Authors A-C", " Jane Austen"], "questions": [{"text": "Mr. Woodhouse loves __________.", "correct": "gruel", "options": ["snowy landscapes", "wedding cake", "brisk breezes"], "explanation": "\n\n\ngruel.\n\n\tHe's a sweet but kinda irritating invalid. \n"}, {"text": "Mrs. Norris loves __________.", "correct": "being in charge", "options": ["Fanny", "Mrs. Price", "resting on the sofa"], "explanation": "\n\n\nbeing in charge.\n\n\tMrs. Norris is an officious _ _ _ _ _. \n"}, {"text": "Miss Bates is a great __________.", "correct": "talker", "options": ["reader", "wit", "grandmother"], "explanation": "\n\n\ntalker.\n\n\tEmma hurts good Miss Bates' feelings during a picnic. \n"}, {"text": "Isabella Thorpe is __________.", "correct": "disloyal", "options": ["dutiful", "oafish", "rich"], "explanation": "\n\n\ndisloyal.\n\n\tShe's a pretty, vulgar, two-faced mantrap. \n"}, {"text": "Mr. Collins worships __________.", "correct": "Lady Catherine de Bourgh", "options": ["Elizabeth Bennet", "Sir William Lucas", "his wife and children"], "explanation": "\n\n\nLady Catherine de Bourgh.\n\n\tMr. Collins may be JA's funniest character. \n"}, {"text": "Sir Walter Elliot loves __________.", "correct": "his own appearance", "options": ["Lady Russell", "his two youngest daughters", "keeping track of his finances"], "explanation": "\n\n\nhis own appearance.\n\n\tWhen Sir Walter isn't admiring his own looks, or Elizabeth's, he's lamenting how frightful everyone else is looking. \n"}, {"text": "Harriet Smith keeps __________.", "correct": "falling in love", "options": ["looking for her father", "reading great works of literature", "bossing Emma around"], "explanation": "\n\n\nfalling in love.\n\n\tShe falls for Robert Martin, Mr. Elton, and Mr. Knightley. Finally she marries Mr. Martin, after all. Emma thinks Harriet's in love with Mr. Frank Churchill, but it's not so. \n"}, {"text": "Mrs. Jennings loves __________.", "correct": "gossip", "options": ["money", "Willoughby", "Colonel Brandon"], "explanation": "\n\n\ngossip.\n\n\tMrs. Jennings turns out to be very good-hearted even though she's kinda vulgar. \n"}, {"text": "Willoughby loves __________.", "correct": "Marianne and money", "options": ["his wife and money", "Colonel Brandon's ward", "Mrs. Jennings"], "explanation": "\n\n\nMarianne and money.\n\n\tHe loves Marianne, but not enough to risk poverty. \n"}, {"text": "Tom Bertram loves __________.", "correct": "society", "options": ["peace and quiet", "Mary Crawford", "his Aunt Norris"], "explanation": "\n\n\nsociety.\n\n\tTom is always telling anecdotes about his many, many friends. \n"}]}