{"id": "49345", "name": "Musical Theatre Lyrics Quiz | Name the Musical | 10 Questions", "type": "", "difficulty": "Very Easy", "tags": ["Home", "Quizzes", "Humanities Trivia", "Lyrics Mixture", "Name the Musical"], "questions": [{"text": "'One brief, shining moment'", "correct": "Camelot", "options": ["Oklahoma", "Music Man", "Annie"], "explanation": "\n\n\nCamelot.\n\n\tClassic line. \n"}, {"text": "'Holy Cow! They'd never believe it!'", "correct": "Sweet Charity", "options": ["She Loves Me!", "Shenandoah", "Chorus Line"], "explanation": "\n\n\nSweet Charity.\n\n\t'If They Could See Me Now ...' Great job by Shirley Maclaine or Gwen Verdon \n"}, {"text": "'Consider yourself at home'", "correct": "Oliver!", "options": ["Peter Pan", "A Funny Thing Happened on the way to the Forum", "The King and I"], "explanation": "\n\n\nOliver!.\n\n\t'Consider Yourself' \n"}, {"text": "'I know a dark secluded place'", "correct": "Pajama Game", "options": ["All That Jazz", "Chicago", "Evita"], "explanation": "\n\n\nPajama Game.\n\n\t'Hernando's Hideaway' \n"}, {"text": "'Anything you can do, I can do better'", "correct": "Annie, Get Your Gun", "options": ["Man of La Mancha", "Fiddler on the Roof", "South Pacific"], "explanation": "\n\n\nAnnie, Get Your Gun.\n\n\tMerman \n"}, {"text": "'When someone walks in your life, you'd just better be sure he's right'", "correct": "Promises, Promises", "options": ["No, No, Nanette", "Show Boat", "Seven Brides for Seven Brothers"], "explanation": "\n\n\nPromises, Promises.\n\n\t'Go When The Going Is Good' - excellent advice \n"}, {"text": "It seems that I'm the only one that I have been thinking of'", "correct": "Stop the World, I Want to Get Off", "options": ["Hello, Dolly", "Damn Yankees", "Mame"], "explanation": "\n\n\nStop the World, I Want to Get Off.\n\n\tNewley's 'What Kind of Fool Am I?' \n"}, {"text": "'Come taste the wine, come hear the band'", "correct": "Cabaret", "options": ["Funny Girl", "Guys and Dolls", "My Fair Lady"], "explanation": "\n\n\nCabaret.\n\n\tTitle song \n"}, {"text": "'Why, it was Jubilation T. Cornpone'", "correct": "Li'l Abner", "options": ["The Roar of the Greasepaint, The Smell of the Crowd", "Applause", "Carousel"], "explanation": "\n\n\nLi'l Abner.\n\n\tFun song. \n"}, {"text": "'Peace and quiet and open air'", "correct": "West Side Story", "options": ["A Little Night Music", "Bye Bye Birdie", "Company"], "explanation": "\n\n\nWest Side Story.\n\n\t'Somewhere' \n"}]}