{"id": "98026", "name": "Movie Debuts of  Five Actors Trivia Quiz | Movies | 5 Questions", "type": "", "difficulty": "Very Easy", "tags": ["Home", "Quizzes", "Movie Trivia", " Something in Common"], "questions": [{"text": "Gary Oldman", "correct": "Remembrance", "options": ["Sid & Nancy", "The Rocky Horror Picture Show", "Pick Up Your Ears"], "explanation": "\n\n\nRemembrance.\n\n\tThis film from 1982 is about the royal navy sent on a 6 month mission to America.  Gary's character name is Daniel. \n"}, {"text": "Michael Keaton", "correct": "A Different Approach", "options": ["All's Fair", "Night Shift", "Mr. Mom"], "explanation": "\n\n\nA Different Approach.\n\n\tMichael plays a filmmaker in this flick from 1978.  \"All's Fair\" was Michael's television debut in 1977 playing Lanny Wolf. \n"}, {"text": "Val Kilmer", "correct": "Top Secret!", "options": ["Chism", "Top Gun", "The Man Who Broke a Thousand Chains"], "explanation": "\n\n\nTop Secret!.\n\n\tVal plays the singer Nick Rivers in this spoof. \n"}, {"text": "Greg Kinnear", "correct": "Blankman", "options": ["Beavis & Butthead Do America", "Sabrina", "Dear God"], "explanation": "\n\n\nBlankman.\n\n\tGreg plays a talk show host.  He was also a talk show host for real in \"Talk Soup\" and \"Later with Greg Kinnear.\" \n"}, {"text": "Hayden Christensen", "correct": "In the Mouth of Madness", "options": ["No Greater Love", "Street Law", "All I Wanna Do"], "explanation": "\n\n\nIn the Mouth of Madness.\n\n\tThis movie is from 1995.  \"No Greater Love\" is a television movie from 1996. \n"}]}